python_redfish-0.4.4.data/data/etc/redfish-client.conf
python_redfish-0.4.4.data/data/share/redfish-client/redfish-client_usage.txt
python_redfish-0.4.4.data/data/share/redfish-client/templates/chassis_info.template
python_redfish-0.4.4.data/data/share/redfish-client/templates/manager_info.template
python_redfish-0.4.4.data/data/share/redfish-client/templates/monitor_info.template
python_redfish-0.4.4.data/data/share/redfish-client/templates/serial_info.template
python_redfish-0.4.4.data/data/share/redfish-client/templates/system_info.template
python_redfish-0.4.4.data/scripts/redfish-check-cartridge
python_redfish-0.4.4.data/scripts/redfish-client
redfish/__init__.py
redfish/config.py
redfish/exception.py
redfish/main.py
redfish/mapping.py
redfish/standard.py
redfish/types.py
redfish/oem/__init__.py
redfish/oem/hpe.py
redfish/tests/test_redfish.py
python_redfish-0.4.4.dist-info/AUTHORS
python_redfish-0.4.4.dist-info/LICENSE
python_redfish-0.4.4.dist-info/METADATA
python_redfish-0.4.4.dist-info/WHEEL
python_redfish-0.4.4.dist-info/pbr.json
python_redfish-0.4.4.dist-info/top_level.txt
python_redfish-0.4.4.dist-info/RECORD
