Metadata-Version: 2.1
Name: python-redfish
Version: 0.4.4
Summary: Reference implementation of Redfish standard client.
Home-page: https://opendev.org/x/python-redfish
Author: Redfish dev team
Author-email: python-redfish@mondorescue.org
License: Apache-2
Platform: UNKNOWN
Classifier: Development Status :: 4 - Beta
Classifier: Environment :: Console
Classifier: Intended Audience :: Information Technology
Classifier: Intended Audience :: System Administrators
Classifier: License :: OSI Approved :: Apache Software License
Classifier: Operating System :: POSIX :: Linux
Classifier: Programming Language :: Python
Classifier: Programming Language :: Python :: 2
Classifier: Programming Language :: Python :: 2.7
Classifier: Programming Language :: Python :: 3
Classifier: Programming Language :: Python :: 3.5
Classifier: Programming Language :: Python :: 3.6
Requires-Dist: pbr (>=0.8)
Requires-Dist: tortilla (>=0.4.1)
Requires-Dist: Jinja2 (>=2.7.3)
Requires-Dist: docopt (>=0.6.2)
Requires-Dist: simplejson (>=3.8.1)
Requires-Dist: requests (>=2.9.1)
Requires-Dist: future (>=0.15.2)
Requires-Dist: configparser (>=3.3.0) ; (python_version < '3')
